LICENSE
MANIFEST.in
README.rst
ez_setup.py
setup.py
dropbox/__init__.py
dropbox/babel_serializers.py
dropbox/babel_validators.py
dropbox/base.py
dropbox/client.py
dropbox/dropbox.py
dropbox/exceptions.py
dropbox/files.py
dropbox/oauth.py
dropbox/rest.py
dropbox/session.py
dropbox/sharing.py
dropbox/trusted-certs.crt
dropbox/users.py
dropbox_compatiable.egg-info/PKG-INFO
dropbox_compatiable.egg-info/SOURCES.txt
dropbox_compatiable.egg-info/dependency_links.txt
dropbox_compatiable.egg-info/not-zip-safe
dropbox_compatiable.egg-info/pbr.json
dropbox_compatiable.egg-info/requires.txt
dropbox_compatiable.egg-info/top_level.txt
test/test_dropbox.py