Metadata-Version: 1.1
Name: dropbox-compatiable
Version: 3.38
Summary: Official Dropbox API Client
Home-page: http://www.dropbox.com/developers
Author: Dropbox
Author-email: dev-platform@dropbox.com
License: Copyright (c) 2015 Dropbox Inc., http://www.dropbox.com/
